suggests/__init__.py
suggests/logger.py
suggests/nets.py
suggests/parsing.py
suggests/suggests.py
suggests/utils.py
suggests-0.1.13.dist-info/LICENSE.txt
suggests-0.1.13.dist-info/METADATA
suggests-0.1.13.dist-info/WHEEL
suggests-0.1.13.dist-info/top_level.txt
suggests-0.1.13.dist-info/RECORD
