Metadata-Version: 2.1
Name: suggests
Version: 0.1.13
Summary: Algorithm auditing tools for search engine autocomplete
Home-page: http://github.com/gitronald/suggests
Author: Ronald E. Robertson
Author-email: rer@ronalderobertson.com
License: MIT
Keywords: suggestions autocomplete google bing
Platform: UNKNOWN
Classifier: Programming Language :: Python :: 3
Classifier: License :: OSI Approved :: MIT License
Requires-Python: ~=3.6
License-File: LICENSE.txt
Requires-Dist: requests
Requires-Dist: pandas
Requires-Dist: numpy
Requires-Dist: bs4
